native_ida_plugin/mysample.dll
native_ida_plugin/mysample.so
native_ida_plugin/mysample_aarch64.dylib
native_ida_plugin/mysample_x86_64.dylib
williballenthin_native_ida_plugin-0.1.0.dist-info/METADATA
williballenthin_native_ida_plugin-0.1.0.dist-info/WHEEL
williballenthin_native_ida_plugin-0.1.0.dist-info/entry_points.txt
williballenthin_native_ida_plugin-0.1.0.dist-info/top_level.txt
williballenthin_native_ida_plugin-0.1.0.dist-info/RECORD
