Metadata-Version: 2.4
Name: williballenthin-native-ida-plugin
Version: 0.1.0
Summary: Example IDA Plugin (native)
Author-email: Willi Ballenthin <wballenthin@google.com>
License-Expression: Apache-2.0
Requires-Python: >=3.9
